[
    {
        "code": "1",
        "name": "Customer1",
        "phone": "0976117366",
        "email": "customer1@gmail.com",
        "identity": "082543505021"
    },
    {
        "code": "2",
        "name": "Customer2",
        "phone": "0947398171",
        "email": "customer2@gmail.com",
        "identity": "018097830747"
    },
    {
        "code": "3",
        "name": "Customer3",
        "phone": "0980568047",
        "email": "customer3@gmail.com",
        "identity": "090475962865"
    },
    {
        "code": "4",
        "name": "Customer4",
        "phone": "0985131304",
        "email": "customer4@gmail.com",
        "identity": "040266691586"
    },
    {
        "code": "5",
        "name": "Customer5",
        "phone": "0982233911",
        "email": "customer5@gmail.com",
        "identity": "037657720962"
    },
    {
        "code": "6",
        "name": "Customer6",
        "phone": "0938675663",
        "email": "customer6@gmail.com",
        "identity": "016827785346"
    },
    {
        "code": "7",
        "name": "Customer7",
        "phone": "0973076526",
        "email": "customer7@gmail.com",
        "identity": "016783604275"
    },
    {
        "code": "8",
        "name": "Customer8",
        "phone": "0997759296",
        "email": "customer8@gmail.com",
        "identity": "049900555301"
    },
    {
        "code": "9",
        "name": "Customer9",
        "phone": "0903670970",
        "email": "customer9@gmail.com",
        "identity": "014564152074"
    },
    {
        "code": "10",
        "name": "Customer10",
        "phone": "0960041758",
        "email": "customer10@gmail.com",
        "identity": "058832215619"
    },
    {
        "code": "11",
        "name": "Customer11",
        "phone": "0989666998",
        "email": "customer11@gmail.com",
        "identity": "058538218316"
    },
    {
        "code": "12",
        "name": "Customer12",
        "phone": "0969898314",
        "email": "customer12@gmail.com",
        "identity": "007046938978"
    },
    {
        "code": "13",
        "name": "Customer13",
        "phone": "0938740866",
        "email": "customer13@gmail.com",
        "identity": "011926371490"
    },
    {
        "code": "14",
        "name": "Customer14",
        "phone": "0923174383",
        "email": "customer14@gmail.com",
        "identity": "096145136204"
    },
    {
        "code": "15",
        "name": "Customer15",
        "phone": "0904050104",
        "email": "customer15@gmail.com",
        "identity": "090928433914"
    },
    {
        "code": "16",
        "name": "Customer16",
        "phone": "0920366828",
        "email": "customer16@gmail.com",
        "identity": "061573796157"
    },
    {
        "code": "17",
        "name": "Customer17",
        "phone": "0983413962",
        "email": "customer17@gmail.com",
        "identity": "053802134661"
    },
    {
        "code": "18",
        "name": "Customer18",
        "phone": "0974683688",
        "email": "customer18@gmail.com",
        "identity": "077909963382"
    },
    {
        "code": "19",
        "name": "Customer19",
        "phone": "0952482163",
        "email": "customer19@gmail.com",
        "identity": "025236077268"
    }
]